[
  {
    "variation": "default",
    "version": "sktwi1xtmkfgx8626",
    "items": [
      {}
    ],
    "primary": {
      "title": [
        {
          "type": "heading1",
          "text": "Garage",
          "spans": []
        }
      ],
      "description": [
        {
          "type": "paragraph",
          "text": "Lorem aute officia enim culpa non nostrud pariatur aliquip amet voluptate. Duis irure et officia sit ullamco id commodo fugiat sit aute eiusmod. Mollit labore velit qui voluptate esse nulla aliqua id voluptate id officia.",
          "spans": []
        }
      ]
    },
    "slice_type": "info_section"
  }
]